pysalesforce/Salesforce.py
pysalesforce/__init__.py
pysalesforce/auth.py
pysalesforce/csv.py
pysalesforce/date.py
pysalesforce/ledger_main.py
pysalesforce/to_blob.py
pysalesforce/useful.py
pysalesforce/tools/__init__.py
pysalesforce/tools/print_colors.py
pysalesforce-0.0.6.dist-info/LICENSE
pysalesforce-0.0.6.dist-info/METADATA
pysalesforce-0.0.6.dist-info/WHEEL
pysalesforce-0.0.6.dist-info/top_level.txt
pysalesforce-0.0.6.dist-info/RECORD
