Metadata-Version: 2.1
Name: pysalesforce
Version: 0.0.6
Summary: A Salesforce connector
Home-page: https://github.com/dacker-team/pysalesforce
Author: Dacker
Author-email: hello@dacker.co
License: UNKNOWN
Platform: UNKNOWN
Classifier: Programming Language :: Python :: 3
Classifier: License :: OSI Approved :: MIT License
Classifier: Operating System :: OS Independent
Requires-Python: >=3
Requires-Dist: dbstream (>=0.0.14)
Requires-Dist: pyyaml (>=5.3.1)
